{
  "name": "PulseU Pack \u2014 Health, Education, Gov",
  "version": "1.0",
  "generated_at": "2025-11-01T16:47:08.669265",
  "count": 4,
  "courses": [
    {
      "course_id": "HEG_PUBLIC-001",
      "title": "Digital Health Compliance Lite",
      "track": "heg_public",
      "reward_pc": 20,
      "stake_pc": 4,
      "grading": "pass_fail",
      "repeatable": true,
      "repeat_lock_first_pass_all": true,
      "mandatory": false,
      "unlock": {
        "after": [
          "SPEC-*",
          "CHAM-*"
        ],
        "min_level": "A"
      }
    },
    {
      "course_id": "HEG_PUBLIC-002",
      "title": "EdTech Course Design",
      "track": "heg_public",
      "reward_pc": 20,
      "stake_pc": 4,
      "grading": "pass_fail",
      "repeatable": true,
      "repeat_lock_first_pass_all": true,
      "mandatory": false,
      "unlock": {
        "after": [
          "SPEC-*",
          "CHAM-*"
        ],
        "min_level": "A"
      }
    },
    {
      "course_id": "HEG_PUBLIC-003",
      "title": "Gov/Grant Writing Basics",
      "track": "heg_public",
      "reward_pc": 20,
      "stake_pc": 4,
      "grading": "pass_fail",
      "repeatable": true,
      "repeat_lock_first_pass_all": true,
      "mandatory": false,
      "unlock": {
        "after": [
          "SPEC-*",
          "CHAM-*"
        ],
        "min_level": "A"
      }
    },
    {
      "course_id": "HEG_PUBLIC-004",
      "title": "Nonprofit Ops Fundamentals",
      "track": "heg_public",
      "reward_pc": 20,
      "stake_pc": 4,
      "grading": "pass_fail",
      "repeatable": true,
      "repeat_lock_first_pass_all": true,
      "mandatory": false,
      "unlock": {
        "after": [
          "SPEC-*",
          "CHAM-*"
        ],
        "min_level": "A"
      }
    }
  ]
}